django_sane_redirects-1.1.0.dist-info/DESCRIPTION.rst
django_sane_redirects-1.1.0.dist-info/METADATA
django_sane_redirects-1.1.0.dist-info/RECORD
django_sane_redirects-1.1.0.dist-info/WHEEL
django_sane_redirects-1.1.0.dist-info/metadata.json
django_sane_redirects-1.1.0.dist-info/top_level.txt
sane_redirects/__init__.py
sane_redirects/admin.py
sane_redirects/apps.py
sane_redirects/middleware.py
sane_redirects/models.py
sane_redirects/migrations/0001_initial.py
sane_redirects/migrations/__init__.py
