Metadata-Version: 2.0
Name: django-sane-redirects
Version: 1.1.0
Summary: django.contrib.redirects without django.contrib.sites
Home-page: https://github.com/feinheit/django-sane-redirects/
Author: Matthias Kestenholz
Author-email: mk@feinheit.ch
License: MIT License
Platform: UNKNOWN
Classifier: Environment :: Web Environment
Classifier: Framework :: Django
Classifier: Intended Audience :: Developers
Classifier: License :: OSI Approved :: MIT License
Classifier: Operating System :: OS Independent
Classifier: Programming Language :: Python
Classifier: Programming Language :: Python :: 3
Classifier: Topic :: Internet :: WWW/HTTP
Classifier: Topic :: Internet :: WWW/HTTP :: Dynamic Content
